txl_jpterm/__init__.py
txl_jpterm/footer.py
txl_jpterm/header.py
txl_jpterm/jpterm.css
txl_jpterm/main.py
txl_jpterm/main_area.py
txl_jpterm-0.3.8.dist-info/METADATA
txl_jpterm-0.3.8.dist-info/WHEEL
txl_jpterm-0.3.8.dist-info/entry_points.txt
txl_jpterm-0.3.8.dist-info/licenses/LICENSE.txt
txl_jpterm-0.3.8.dist-info/RECORD
